servcetl/__init__.py
servcetl/dag.py
servcetl/payload.py
servcetl/py.typed
servcetl/trigger.py
servcetl-0.2.2.dist-info/licenses/LICENSE
servcetl-0.2.2.dist-info/METADATA
servcetl-0.2.2.dist-info/WHEEL
servcetl-0.2.2.dist-info/top_level.txt
servcetl-0.2.2.dist-info/RECORD
