Metadata-Version: 2.4
Name: servcetl
Version: 0.2.2
Summary: ETL Typings for serv-c
Author-email: Yusuf Ali <ali@yusuf.email>
Project-URL: Homepage, https://github.com/serv-c/servc-etl-python
Project-URL: Bug Tracker, https://github.com/serv-c/servc-etl-python/issues
Project-URL: Repository, https://github.com/serv-c/servc-etl-python.git
Project-URL: Documentation, https://docs.servc.io/
Classifier: Programming Language :: Python :: 3
Classifier: License :: OSI Approved :: MIT License
Classifier: Operating System :: OS Independent
Requires-Python: >=3.11
License-File: LICENSE
Requires-Dist: servc==1.11.5
Dynamic: license-file
